probinet/__init__.py
probinet/main.py
probinet/py.typed
probinet/types.py
probinet/version.py
probinet/data/input/highschool_network.dat
probinet/data/input/synthetic_binary_network.dat
probinet/data/input/synthetic_design_matrix.csv
probinet/data/input/synthetic_dynamic_network.dat
probinet/data/input/synthetic_multilayer_network.csv
probinet/data/input/synthetic_network_with_anomalies.dat
probinet/data/input/synthetic_undirected_network.csv
probinet/data/input/synthetic_weighted_network.dat
probinet/data/model/setting_synthetic_data_CRep.yaml
probinet/evaluation/__init__.py
probinet/evaluation/community_detection.py
probinet/evaluation/covariate_prediction.py
probinet/evaluation/expectation_computation.py
probinet/evaluation/likelihood.py
probinet/evaluation/link_prediction.py
probinet/input/__init__.py
probinet/input/loader.py
probinet/input/preprocessing.py
probinet/input/stats.py
probinet/model_selection/__init__.py
probinet/model_selection/acd_cross_validation.py
probinet/model_selection/crep_cross_validation.py
probinet/model_selection/cross_validation.py
probinet/model_selection/dyncrep_cross_validation.py
probinet/model_selection/jointcrep_cross_validation.py
probinet/model_selection/main.py
probinet/model_selection/masking.py
probinet/model_selection/mtcov_cross_validation.py
probinet/model_selection/parameter_search.py
probinet/models/__init__.py
probinet/models/acd.py
probinet/models/base.py
probinet/models/classes.py
probinet/models/constants.py
probinet/models/crep.py
probinet/models/dyncrep.py
probinet/models/jointcrep.py
probinet/models/mtcov.py
probinet/synthetic/__init__.py
probinet/synthetic/anomaly.py
probinet/synthetic/base.py
probinet/synthetic/dynamic.py
probinet/synthetic/multilayer.py
probinet/synthetic/reciprocity.py
probinet/utils/__init__.py
probinet/utils/matrix_operations.py
probinet/utils/tools.py
probinet/visualization/__init__.py
probinet/visualization/plot.py
probinet-1.1.dist-info/licenses/LICENSE.md
probinet-1.1.dist-info/METADATA
probinet-1.1.dist-info/WHEEL
probinet-1.1.dist-info/entry_points.txt
probinet-1.1.dist-info/top_level.txt
probinet-1.1.dist-info/RECORD
