Metadata-Version: 2.4
Name: probinet
Version: 1.1
Summary: Python package for probabilistic network analysis.
Author-email: Diego Baptista Theuerkauf <diego.theuerkauf@tue.mpg.de>
Maintainer-email: Diego Baptista Theuerkauf <diego.theuerkauf@tue.mpg.de>
Project-URL: documentation, https://mpi-is.github.io/probinet/
Project-URL: source, https://github.com/MPI-IS/probinet
Project-URL: tracker, https://github.com/MPI-IS/probinet/issues
Classifier: Programming Language :: Python
Classifier: Programming Language :: Python :: 3
Classifier: Programming Language :: Python :: 3.10
Classifier: Programming Language :: Python :: 3.11
Classifier: Programming Language :: Python :: 3.12
Classifier: License :: OSI Approved :: GNU General Public License v3 (GPLv3)
Classifier: Typing :: Typed
Classifier: Topic :: Software Development
Classifier: Topic :: Scientific/Engineering
Classifier: Operating System :: Microsoft :: Windows
Classifier: Operating System :: POSIX
Classifier: Operating System :: Unix
Classifier: Operating System :: MacOS
Requires-Python: <3.13,>=3.10
License-File: LICENSE.md
Requires-Dist: jupyter
Requires-Dist: matplotlib
Requires-Dist: networkx
Requires-Dist: numpy
Requires-Dist: pandas
Requires-Dist: pyyaml
Requires-Dist: pytest
Requires-Dist: scikit-learn
Requires-Dist: scipy
Requires-Dist: sparse
Requires-Dist: seaborn
Provides-Extra: dev
Requires-Dist: autopep8; extra == "dev"
Requires-Dist: coverage; extra == "dev"
Requires-Dist: coverage2clover; extra == "dev"
Requires-Dist: isort; extra == "dev"
Requires-Dist: jupyter; extra == "dev"
Requires-Dist: matplotlib; extra == "dev"
Requires-Dist: mypy; extra == "dev"
Requires-Dist: myst_nb; extra == "dev"
Requires-Dist: nbconvert; extra == "dev"
Requires-Dist: pylint; extra == "dev"
Requires-Dist: sphinxcontrib.bibtex; extra == "dev"
Requires-Dist: sphinxcontrib.napoleon; extra == "dev"
Requires-Dist: sphinx_book_theme; extra == "dev"
Requires-Dist: sphinx-copybutton; extra == "dev"
Requires-Dist: tox; extra == "dev"
Requires-Dist: unittest-xml-reporting; extra == "dev"
Dynamic: license-file
